CHANGELOG.md
hikvision_isapi_cli/__init__.py
hikvision_isapi_cli/api/__init__.py
hikvision_isapi_cli/api/default/__init__.py
hikvision_isapi_cli/api/default/get_isapi_system_network_interfaces.py
hikvision_isapi_cli/api/default/put_isapi_system_device_info.py
hikvision_isapi_cli/api/default/put_isapi_system_two_way_audio_channels_channel_id_audio_data.py
hikvision_isapi_cli/api/default/session_heartbeat.py
hikvision_isapi_cli/api/default/session_login.py
hikvision_isapi_cli/api/default/session_login_capabilities.py
hikvision_isapi_cli/api/isapi/__init__.py
hikvision_isapi_cli/api/isapi/callstatus.py
hikvision_isapi_cli/api/isapi/callstatus_capabilities_format_json.py
hikvision_isapi_cli/api/isapi/capabilities.py
hikvision_isapi_cli/api/isapi/capabilities1.py
hikvision_isapi_cli/api/isapi/capabilties.py
hikvision_isapi_cli/api/isapi/channels.py
hikvision_isapi_cli/api/isapi/channels2.py
hikvision_isapi_cli/api/isapi/channels_1_audiodata.py
hikvision_isapi_cli/api/isapi/channels_1_capabilities.py
hikvision_isapi_cli/api/isapi/channels_1_close.py
hikvision_isapi_cli/api/isapi/channels_1_open.py
hikvision_isapi_cli/api/isapi/channels_1_picture.py
hikvision_isapi_cli/api/isapi/devicecommunication_format_json.py
hikvision_isapi_cli/api/isapi/deviceid.py
hikvision_isapi_cli/api/isapi/deviceid_capabilities.py
hikvision_isapi_cli/api/isapi/deviceinfo.py
hikvision_isapi_cli/api/isapi/door.py
hikvision_isapi_cli/api/isapi/door_capabilities.py
hikvision_isapi_cli/api/isapi/encryption_format_json.py
hikvision_isapi_cli/api/isapi/get_isapi_streaming_channels.py
hikvision_isapi_cli/api/isapi/index1.py
hikvision_isapi_cli/api/isapi/inputs_channels.py
hikvision_isapi_cli/api/isapi/status.py
hikvision_isapi_cli/api/isapi/usercheck.py
hikvision_isapi_cli/api/isapi/userpermission1.py
hikvision_isapi_cli/api/isapi/users.py
hikvision_isapi_cli/client.py
hikvision_isapi_cli/errors.py
hikvision_isapi_cli/models/__init__.py
hikvision_isapi_cli/models/root_type_for_call_status.py
hikvision_isapi_cli-1.2.1.dist-info/METADATA
hikvision_isapi_cli-1.2.1.dist-info/WHEEL
hikvision_isapi_cli-1.2.1.dist-info/RECORD
