Metadata-Version: 2.1
Name: hikvision-isapi-cli
Version: 1.2.1
Summary: A client library for accessing Hikvision ISAPI and more
Author: mmascia
Requires-Python: >=3.11,<4.0
Classifier: Programming Language :: Python :: 3
Classifier: Programming Language :: Python :: 3.11
Requires-Dist: httpx (==0.24.1)
Requires-Dist: pytest (==7.3.1)
Requires-Dist: pytest-aiohttp (==1.0.4)
Requires-Dist: pytest-asyncio (==0.20.3)
Requires-Dist: pytest-cov (==3.0.0)
Requires-Dist: pytest-freezer (==0.4.6)
Requires-Dist: pytest-picked (==0.4.6)
Requires-Dist: pytest-socket (==0.5.1)
Requires-Dist: pytest-sugar (==0.9.6)
Requires-Dist: pytest-test-groups (==1.0.3)
Requires-Dist: pytest-timeout (==2.1.0)
Requires-Dist: pytest-unordered (==0.5.2)
Requires-Dist: pytest-xdist (==3.2.1)
Requires-Dist: python-dateutil (==2.8.2)
Requires-Dist: xmltodict (==0.13.0)
